{"sections":{"main":{"type":"page","disabled":true,"settings":{"kicker":"","kicker_size":3,"show_title":true,"title_size":8,"show_content":true,"content_size":5,"align_text":"text-left","text_color":"text--neutral","bg":"palette--light bg--neutral","width":"wrapper","padding_top":36,"padding_bottom":36}},"section_hero_xXCEGj":{"type":"section-hero","blocks":{"kicker_KHjAwJ":{"type":"kicker","settings":{"kicker":"Workplace | Healthcare","enable_line":false,"text_size":4}},"heading_pKUDYh":{"type":"heading","settings":{"title":"Leading New England Health Care Company Headquarters","text_size":9}},"text_7YyWWq":{"type":"text","settings":{"richtext":"<p>New England<\/p>","text_size":6}}},"block_order":["kicker_KHjAwJ","heading_pKUDYh","text_7YyWWq"],"settings":{"image":"shopify:\/\/shop_images\/Artlifting_6.20.25_Canton_Final-04.jpg","height":"use_screen_two_thirds","overlay_opacity":25,"overlay_color":"#000000","enable_overlay_text":true,"preload_image":false,"content_width":2000,"text_align":"align--bottom-left","text_color":"text--white","color_bg":"hero__content--transparent","width":"wrapper--none","padding_top":0,"padding_bottom":0}},"section_gallery_tcEqpm":{"type":"section-gallery","blocks":{"image_zwLH8N":{"type":"image","settings":{"image":"shopify:\/\/shop_images\/Artlifting_6.20.25_Canton_Final-02.jpg","link":""}},"image_MayG63":{"type":"image","settings":{"image":"shopify:\/\/shop_images\/Artlifting_6.20.25_Canton_Final-09.jpg","link":""}},"image_VKixbN":{"type":"image","settings":{"image":"shopify:\/\/shop_images\/Artlifting_6.20.25_Canton_Final-11.jpg","link":""}},"image_Gmn88F":{"type":"image","settings":{"image":"shopify:\/\/shop_images\/Artlifting_6.20.25_Canton_Final-13.jpg","link":""}},"image_t4wRAY":{"type":"image","settings":{"image":"shopify:\/\/shop_images\/Artlifting_6.20.25_Canton_Final-17.jpg","link":""}},"image_EpqRPd":{"type":"image","settings":{"image":"shopify:\/\/shop_images\/Artlifting_6.20.25_Canton_Final-19.jpg","link":""}},"image_nBH6UD":{"type":"image","settings":{"image":"shopify:\/\/shop_images\/Artlifting_6.20.25_Canton_Final-23.jpg","link":""}},"image_mnDA43":{"type":"image","settings":{"image":"shopify:\/\/shop_images\/Artlifting_6.20.25_Canton_Final-24.jpg","link":""}}},"block_order":["image_zwLH8N","image_MayG63","image_VKixbN","image_Gmn88F","image_t4wRAY","image_EpqRPd","image_nBH6UD","image_mnDA43"],"settings":{"scale_image":true,"wh_ratio":1.5,"bg":"palette--light bg--neutral","add_gutters":true,"progress_bar":"mobile","grid_large":3,"grid_medium":2,"grid_mobile":1.2,"width":"wrapper","padding_top":36,"padding_bottom":36}},"section_custom_content_CFhtJp":{"type":"section-custom-content","blocks":{"text_GPU8Xb":{"type":"text","settings":{"kicker":"Project Highlights","enable_line":true,"kicker_text_size":5,"title":"","text":"<ul><li><strong>Property Details: <\/strong>Corporate headquarters for a leading New England health care company<\/li><li><strong>Property Size:<\/strong> 500,000 sq. ft.<\/li><li><strong>Services Provided:<\/strong> Curated art program for large-scale print reproductions, along with full installation services<\/li><\/ul>","font_size":4,"text_columns":1,"align_text":"text-left","button_text":"","button_url":"","button_color":"btn--neutral","button_style":"btn-text-thick-line","text_color":"text--neutral","bg_color":""}},"text_FUbyW7":{"type":"text","settings":{"kicker":"Featured Artists","enable_line":true,"kicker_text_size":5,"title":"","text":"<p><a href=\"https:\/\/www.artlifting.com\/es\/collections\/aimee-hofmann\"><span style=\"text-decoration:underline\">Aimee Hofmann<\/span><\/a>, <a href=\"https:\/\/www.artlifting.com\/es\/collections\/billy-megargel\"><span style=\"text-decoration:underline\">Billy Megargel,<\/span><\/a><a href=\"https:\/\/www.artlifting.com\/collections\/bonnie-salser\"><span style=\"text-decoration:underline\">Bonnie Salser<\/span><\/a>, <a href=\"https:\/\/www.artlifting.com\/collections\/charles-blackwell\"><span style=\"text-decoration:underline\">Charles Blackwell<\/span><\/a>, <a href=\"https:\/\/www.artlifting.com\/collections\/chris-marinez\"><span style=\"text-decoration:underline\">Chris Marinez<\/span><\/a>, <a href=\"https:\/\/www.artlifting.com\/collections\/christina-culverhouse\"><span style=\"text-decoration:underline\">Christina Culverhouse<\/span><\/a>, <a href=\"https:\/\/www.artlifting.com\/collections\/christine-nelson\"><span style=\"text-decoration:underline\">Christine Nelson<\/span><\/a>, <a href=\"https:\/\/www.artlifting.com\/collections\/diyah-najah\"><span style=\"text-decoration:underline\">Diyah Najah<\/span><\/a>, <a href=\"https:\/\/www.artlifting.com\/collections\/elizabeth-belstraz\"><span style=\"text-decoration:underline\">Elizabeth Belstraz<\/span><\/a>,<a href=\"https:\/\/www.artlifting.com\/collections\/han-huisman\"><span style=\"text-decoration:underline\"> Han Huisman<\/span><\/a>, <a href=\"https:\/\/www.artlifting.com\/collections\/ian-shearer\"><span style=\"text-decoration:underline\">Ian Shearer<\/span><\/a>, <a href=\"https:\/\/www.artlifting.com\/collections\/jeff-powers\"><span style=\"text-decoration:underline\">Jeffrey Powers<\/span><\/a>, <a href=\"https:\/\/www.artlifting.com\/collections\/johnson-simon\"><span style=\"text-decoration:underline\">Johnson Simon<\/span><\/a>, <a href=\"https:\/\/www.artlifting.com\/collections\/jude-chase\"><span style=\"text-decoration:underline\">Jude Chase<\/span><\/a>, <a href=\"https:\/\/www.artlifting.com\/collections\/juliana-alonso\"><span style=\"text-decoration:underline\">Juliana Alonso<\/span><\/a>, <a href=\"https:\/\/www.artlifting.com\/collections\/kennedy-nganga\"><span style=\"text-decoration:underline\">Kennedy Nganga<\/span><\/a>, <a href=\"https:\/\/www.artlifting.com\/collections\/lisa-murphy\"><span style=\"text-decoration:underline\">Lisa Murphy<\/span><\/a>, <a href=\"https:\/\/www.artlifting.com\/collections\/lucas-farlow\"><span style=\"text-decoration:underline\">Lucas Farlow<\/span><\/a>, <a href=\"https:\/\/www.artlifting.com\/collections\/madison-elyse-rubenstein\"><span style=\"text-decoration:underline\">Madison Elyse Rubenstein<\/span><\/a>, <a href=\"https:\/\/www.artlifting.com\/collections\/matthew-breedlove\"><span style=\"text-decoration:underline\">Matthew Breedlove<\/span><\/a>, <a href=\"https:\/\/www.artlifting.com\/collections\/michaels-lyric\"><span style=\"text-decoration:underline\">Michaels Lyric<\/span><\/a>, <a href=\"https:\/\/www.artlifting.com\/collections\/nick-morse\"><span style=\"text-decoration:underline\">Nick Morse<\/span><\/a>, <a href=\"https:\/\/www.artlifting.com\/collections\/quana-madison\"><span style=\"text-decoration:underline\">Quána Madison<\/span><\/a>, <a href=\"https:\/\/www.artlifting.com\/collections\/selah-rose\"><span style=\"text-decoration:underline\">Selah Rose<\/span><\/a>, <a href=\"https:\/\/www.artlifting.com\/collections\/sierra-barnes\"><span style=\"text-decoration:underline\">Sierra Barnes<\/span><\/a>, <a href=\"https:\/\/www.artlifting.com\/collections\/stacey-williams\"><span style=\"text-decoration:underline\">Stacey Williams<\/span><\/a>, <a href=\"https:\/\/www.artlifting.com\/collections\/yasmine-iskander\"><span style=\"text-decoration:underline\">Yasmine Iskander<\/span><\/a>.<\/p>","font_size":4,"text_columns":1,"align_text":"text-left","button_text":"","button_url":"","button_color":"btn--neutral","button_style":"btn-text-thick-line","text_color":"text--neutral","bg_color":""}}},"block_order":["text_GPU8Xb","text_FUbyW7"],"name":"Custom content","settings":{"height":"use_screen_one_fifth","brick_gutter":20,"borders":false,"vertalign":"valign--top","bg_color":"","preload_image":false,"width":"wrapper","padding_top":36,"padding_bottom":0}},"section_custom_content_kMAXdn":{"type":"section-custom-content","blocks":{"text_F7rw9M":{"type":"text","settings":{"kicker":"Key Takeaways","enable_line":true,"kicker_text_size":5,"title":"","text":"<ul><li>A values-driven art strategy featuring curated print reproductions aligns with brand values and creates a cohesive, inspiring workplace environment.<\/li><li>Artwork by diverse ArtLifting artists reflects the organization’s commitment to wellbeing and inclusion, reinforcing its purpose of advancing health equity and community care.<\/li><\/ul>","font_size":4,"text_columns":1,"align_text":"text-left","button_text":"","button_url":"","button_color":"btn--neutral","button_style":"btn-text-thick-line","text_color":"text--neutral","bg_color":""}}},"block_order":["text_F7rw9M"],"name":"Custom content","settings":{"height":"use_screen_one_fifth","brick_gutter":20,"borders":false,"vertalign":"valign--top","bg_color":"","preload_image":false,"width":"wrapper","padding_top":0,"padding_bottom":0}},"section_richtext_CBpRyR":{"type":"section-richtext","blocks":{"text_RQWJaW":{"type":"text","settings":{"text":"<h5><strong>“As someone who’s walked a long path of healing, it’s deeply meaningful to know my art lives within [the headquarters] of a company grounded in compassion and support. It feels like more than a sale — it’s a powerful alignment between my story and their mission to help others feel cared for regardless of their life stage. Thank you for giving my work a home where it can continue to offer comfort and connection.”<\/strong><\/h5><p><br\/>- <a href=\"https:\/\/www.artlifting.com\/collections\/juliana-alonso\"><span style=\"text-decoration:underline\">Juliana Alonso<\/span><\/a>, ArtLifting Artist<\/p>","text_size":4,"text_columns":1}}},"block_order":["text_RQWJaW"],"settings":{"align_text":"text-left","text_color":"text--neutral","bg":"palette--light bg--neutral","content_width":850,"width":"wrapper","padding_top":0,"padding_bottom":36}},"section_richtext_mCYk3E":{"type":"section-richtext","blocks":{"heading_BKPaEp":{"type":"heading","settings":{"heading":"Creating a Welcoming Healthcare Headquarters with Curated Art","text_size":8}},"text_igWW9A":{"type":"text","settings":{"text":"<p>ArtLifting partnered with a leading New England health care company to transform its headquarters into a vibrant, inclusive environment that reflects its commitment to workplace wellbeing and belonging. <\/p><p><br\/>The curatorial approach aligned each wing of the building with a color theme and brand value — embrace learning, own outcomes, grow together, and build community — while connecting directly to the organization’s employee resource groups. This strategy ensures the artwork enlivens a modern, neutral space while resonating with the lived experiences of staff and the patients they serve.<\/p><p><br\/>The collection features a rotation program of abstract and figurative works by 27 ArtLifting artists, with emphasis on local and underrepresented voices. Print reproductions were thoughtfully placed to create impact in high-traffic spaces, communal areas, and executive offices. With each rotation, the client’s teams connect with different stories and styles of artwork. <\/p><p><br\/>By integrating art as a visual anchor and a storytelling tool, the project reinforces the organization’s leadership in health equity, wellness, and inclusion while cultivating a more welcoming and inspiring workplace.<\/p>","text_size":4,"text_columns":1}}},"block_order":["heading_BKPaEp","text_igWW9A"],"name":"Rich text","settings":{"align_text":"text-left","text_color":"text--neutral","bg":"palette--light bg--neutral","content_width":850,"width":"wrapper","padding_top":36,"padding_bottom":36}},"section_richtext_8N4fUc":{"type":"section-richtext","blocks":{"text_nwbWn8":{"type":"text","settings":{"text":"<p><strong>Images<\/strong><\/p><p>1. Banner: Two large abstract paintings hang in a bright hallway. <em>Always In<\/em> (left) by <a href=\"https:\/\/www.artlifting.com\/collections\/madison-elyse-rubenstein\"><span style=\"text-decoration:underline\">Madison Elyse Rubenstein<\/span><\/a> bursts with swirling strokes of red, turquoise, black, and yellow, while <em>Relentless Spirit of Positive Transformation<\/em> (right) by <a href=\"https:\/\/www.artlifting.com\/collections\/quana-madison\"><span style=\"text-decoration:underline\">Quána Madison<\/span><\/a> features layered circular forms in pink, purple, and blue on a dark background.<\/p><p><br\/>2. Vibrant, abstract prints line a white corridor. <em>Colorful Chaotic World 3<\/em> (right) by <a href=\"https:\/\/www.artlifting.com\/collections\/christina-culverhouse\"><span style=\"text-decoration:underline\">Christina Culverhouse<\/span><\/a> shows layered purple shapes, the middle work, <em>Feelings: Uncategorized,<\/em> by <a href=\"https:\/\/www.artlifting.com\/collections\/madison-elyse-rubenstein\"><span style=\"text-decoration:underline\">Madison Elyse Rubenstein<\/span><\/a> combines overlapping patches of pink, orange, and teal. <\/p><p><\/p><p><br\/>3. Hanging above a reception desk, <em>Abstract 2021-0519-15<\/em> by <a href=\"https:\/\/www.artlifting.com\/collections\/han-huisman\"><span style=\"text-decoration:underline\">Han Huisman<\/span><\/a> presents bold swaths of blue, black, white, and earthy tones with textured drips and organic marks.<\/p><p><\/p><p><br\/>4. Displayed beside a glass-walled meeting room, <em>Incantation<\/em> by <a href=\"https:\/\/www.artlifting.com\/collections\/ian-shearer\"><span style=\"text-decoration:underline\">Ian Shearer<\/span><\/a> depicts a shoreline at sunset in soft pinks, purples, and blues, with trees and water reflecting the fading light.<br\/><br\/><\/p><p><\/p><p>5. Two figurative works by <a href=\"https:\/\/www.artlifting.com\/collections\/lisa-murphy\"><span style=\"text-decoration:underline\">Lisa Murphy<\/span><\/a> hang side by side. <em>As One <\/em>(left) shows a pair of faces outlined in white over a purple background, while <em>Together<\/em> (right) features embracing figures drawn in white on a deep blue surface.<\/p><p><br\/>6. <em>Reaching for the Stars<\/em> by <a href=\"https:\/\/www.artlifting.com\/collections\/selah-rose\"><span style=\"text-decoration:underline\">Selah Rose<\/span><\/a> is a large abstract painting in shades of purple, pink, and blue with cloud-like textures, displayed on a white wall near an open hallway.<\/p><p><br\/>7. A series of prints by <a href=\"https:\/\/www.artlifting.com\/collections\/yasmine-iskander\"><span style=\"text-decoration:underline\">Yasmine Iskander<\/span><\/a>, <a href=\"https:\/\/www.artlifting.com\/collections\/kennedy-nganga\"><span style=\"text-decoration:underline\">Kennedy Nganga<\/span><\/a>, and <a href=\"https:\/\/www.artlifting.com\/collections\/lisa-murphy\"><span style=\"text-decoration:underline\">Lisa Murphy<\/span><\/a> hangs above a row of lounge chairs. <\/p><p><br\/>8. Two prints by <a href=\"https:\/\/www.artlifting.com\/collections\/michaels-lyric\"><span style=\"text-decoration:underline\">Michaels Lyric<\/span><\/a> are mounted on a wall near a modern staircase, both capturing people in dynamic outdoor scenes with expressive movement and bright, layered colors. <\/p><p><br\/>9. A gallery wall features prints by multiple ArtLifting artists, arranged salon-style above a cushioned bench. The collection includes portraits, abstract figures, and expressive color studies in a range of styles and tones.<\/p>","text_size":4,"text_columns":1}}},"block_order":["text_nwbWn8"],"settings":{"align_text":"text-left","text_color":"text--neutral","bg":"palette--light bg--neutral","content_width":850,"width":"wrapper","padding_top":36,"padding_bottom":36}},"section_contact_nRHrHF":{"type":"section-contact","blocks":{"select_QzKLrA":{"type":"select","settings":{"title":"Topic","required":true,"label_one":"General Inquiries","label_two":"Consumer Sales","label_three":"Corporate Sales","label_four":"Artists","label_five":"Partnerships","label_six":""}},"email_KepGKR":{"type":"email","settings":{"title":"Name","required":true}},"text_QzTHDz":{"type":"text","settings":{"title":"E-mail","required":true}},"telephone_dV3qVe":{"type":"telephone","settings":{"title":"Phone","required":false}},"text_wE8daA":{"type":"text","settings":{"title":"How did you hear about us?","required":false}},"body_4tFmwh":{"type":"body","settings":{"title":"Message","required":true}}},"block_order":["select_QzKLrA","email_KepGKR","text_QzTHDz","telephone_dV3qVe","text_wE8daA","body_4tFmwh"],"settings":{"title":"Let's talk about art!","align_text":"text-left","button_size":"btn--large","button_color":"btn--secondary","button_style":"btn","text_color":"text--neutral","bg":"palette--light bg--neutral","width":"wrapper--narrow","padding_top":36,"padding_bottom":36}},"section_custom_content_Dc8j3k":{"type":"section-custom-content","blocks":{"image_8MHhaF":{"type":"image","settings":{"image":"shopify:\/\/shop_images\/Wallcoverings_Stoneleigh_Installation_Photo_Allen_Chamberland_2.jpg","overlay_opacity":25,"overlay_color":"#000000","enable_overlay_text":true,"kicker":"","enable_line":false,"kicker_text_size":5,"title":"Portfolio","richtext":"","text_align":"align--middle-center","text_color":"text--white","link_text":"","link":"https:\/\/www.artlifting.com\/cdn\/shop\/files\/Prints_BoA_Installation_Photo_Rudolph_Jean-Louis.jpg?v=1707353806&width=1200","button_color":"btn--white","button_style":"btn"}},"image_nDTXLR":{"type":"image","settings":{"image":"shopify:\/\/shop_images\/020824-Artlifting-Mural-11.jpg","overlay_opacity":25,"overlay_color":"#000000","enable_overlay_text":true,"kicker":"","enable_line":false,"kicker_text_size":5,"title":"Services","richtext":"","text_align":"align--middle-center","text_color":"text--white","link_text":"","link":"https:\/\/www.artlifting.com\/pages\/services","button_color":"btn--white","button_style":"btn"}}},"block_order":["image_8MHhaF","image_nDTXLR"],"settings":{"height":"use_screen_one_half","brick_gutter":12,"borders":false,"vertalign":"valign--middle","bg_color":"","preload_image":false,"width":"wrapper","padding_top":36,"padding_bottom":36}}},"order":["main","section_hero_xXCEGj","section_gallery_tcEqpm","section_custom_content_CFhtJp","section_custom_content_kMAXdn","section_richtext_CBpRyR","section_richtext_mCYk3E","section_richtext_8N4fUc","section_contact_nRHrHF","section_custom_content_Dc8j3k"]}